README.rst
minirepo.py
setup.py
minirepo.egg-info/PKG-INFO
minirepo.egg-info/SOURCES.txt
minirepo.egg-info/dependency_links.txt
minirepo.egg-info/entry_points.txt
minirepo.egg-info/top_level.txt