Metadata-Version: 1.1
Name: minirepo
Version: 1.0.3
Summary: Create a local pypi repository to use pip off-line
Home-page: https://github.com/sganis/minirepo
Author: sganis
Author-email: sganis@gmail.com
License: MIT
Keywords: minirepo development pip mirror packages offline repository
Platform: UNKNOWN
Classifier: Development Status :: 3 - Alpha
Classifier: Intended Audience :: Developers
Classifier: Topic :: Software Development :: Build Tools
Classifier: License :: OSI Approved :: MIT License
Classifier: Programming Language :: Python :: 2.7
Classifier: Programming Language :: Python :: 3.4
